ReactNativeRumenZhinan/README.md
ReactNativeRumenZhinan/__init__.py
ReactNativeRumenZhinan/__main__.py
ReactNativeRumenZhinan/file.epub
ReactNativeRumenZhinan/index.html
ReactNativeRumenZhinan/css/__init__.py
ReactNativeRumenZhinan/css/annotations.css
ReactNativeRumenZhinan/css/main.css
ReactNativeRumenZhinan/css/normalize.css
ReactNativeRumenZhinan/css/popup.css
ReactNativeRumenZhinan/font/__init__.py
ReactNativeRumenZhinan/font/fontello.eot
ReactNativeRumenZhinan/font/fontello.svg
ReactNativeRumenZhinan/font/fontello.ttf
ReactNativeRumenZhinan/font/fontello.woff
ReactNativeRumenZhinan/img/__init__.py
ReactNativeRumenZhinan/img/annotator-glyph-sprite.png
ReactNativeRumenZhinan/img/annotator-icon-sprite.png
ReactNativeRumenZhinan/img/apple-touch-icon.png
ReactNativeRumenZhinan/img/cancelfullscreen.png
ReactNativeRumenZhinan/img/close.png
ReactNativeRumenZhinan/img/fullscreen.png
ReactNativeRumenZhinan/img/loader.gif
ReactNativeRumenZhinan/img/menu-icon.png
ReactNativeRumenZhinan/img/save.png
ReactNativeRumenZhinan/img/saved.png
ReactNativeRumenZhinan/img/settings-s.png
ReactNativeRumenZhinan/img/settings.png
ReactNativeRumenZhinan/img/star.png
ReactNativeRumenZhinan/js/__init__.py
ReactNativeRumenZhinan/js/epub.js
ReactNativeRumenZhinan/js/epub.min.js
ReactNativeRumenZhinan/js/epub.min.map
ReactNativeRumenZhinan/js/hooks.min.js
ReactNativeRumenZhinan/js/hooks.min.map
ReactNativeRumenZhinan/js/reader.js
ReactNativeRumenZhinan/js/reader.js.map
ReactNativeRumenZhinan/js/reader.min.js
ReactNativeRumenZhinan/js/reader.min.map
ReactNativeRumenZhinan/js/hooks/__init__.py
ReactNativeRumenZhinan/js/hooks/extensions/__init__.py
ReactNativeRumenZhinan/js/hooks/extensions/highlight.js
ReactNativeRumenZhinan/js/libs/__init__.py
ReactNativeRumenZhinan/js/libs/jquery.min.js
ReactNativeRumenZhinan/js/libs/localforage.min.js
ReactNativeRumenZhinan/js/libs/screenfull.js
ReactNativeRumenZhinan/js/libs/screenfull.min.js
ReactNativeRumenZhinan/js/libs/zip.min.js
react_native_rumen_zhinan-2024.3.1.0.dist-info/METADATA
react_native_rumen_zhinan-2024.3.1.0.dist-info/WHEEL
react_native_rumen_zhinan-2024.3.1.0.dist-info/entry_points.txt
react_native_rumen_zhinan-2024.3.1.0.dist-info/top_level.txt
react_native_rumen_zhinan-2024.3.1.0.dist-info/RECORD
